{
	"info": {
		"_postman_id": "60468437-796a-4ace-b91f-a69a4567eae5",
		"name": "getpreorderpoolitems-QA",
		"schema": "https://schema.getpostman.com/json/collection/v2.1.0/collection.json"
	},
	"item": [
		{
			"name": "TC01_Validate the API response",
			"request": {
				"method": "GET",
				"header": [
					{
						"key": "Accept",
						"value": "application/json, text/plain, */*"
					},
					{
						"key": "Accept-Language",
						"value": "en-GB,en-US;q=0.9,en;q=0.8"
					},
					{
						"key": "Cache-Control",
						"value": "no-cache, no-store, must-revalidate"
					},
					{
						"key": "Connection",
						"value": "keep-alive"
					},
					{
						"key": "Cookie",
						"value": "_ga=GA1.2.1629569301.1665497888; _fbp=fb.1.1665497888654.1290370928; __qca=P0-83208946-1665497888970"
					},
					{
						"key": "Expires",
						"value": "0"
					},
					{
						"key": "Origin",
						"value": "https://test1.groceryoutlet.com"
					},
					{
						"key": "Pragma",
						"value": "no-cache"
					},
					{
						"key": "Referer",
						"value": "https://test1.groceryoutlet.com/"
					},
					{
						"key": "Sec-Fetch-Dest",
						"value": "empty"
					},
					{
						"key": "Sec-Fetch-Mode",
						"value": "cors"
					},
					{
						"key": "Sec-Fetch-Site",
						"value": "same-site"
					},
					{
						"key": "User-Agent",
						"value": "Mozilla/5.0 (X11; Linux x86_64) AppleWebKit/537.36 (KHTML, like Gecko) Chrome/103.0.0.0 Safari/537.36"
					},
					{
						"key": "X-XSRF-Token",
						"value": "L3BitUIApWiGXGVW7QtlP7smL5XIoMbQ3PTCyw1SBX8WlJJMBPCtfz3OfaTHEYCywv-5-vvubWKvdR05FhhncjsNdrA1:p4N8w8Pkrw14fMEolytxt-Tj1A6UayE_nN_r4LDwQvTMmKX2QGqxmX0O35whiw9QCz4GqJ-6cwyqTIjLEvBbhOgjj44Y2N7xwZps610ba86va3ev5SYaAjLzrcKDWXWICil-jA2"
					},
					{
						"key": "api-token",
						"value": "Ac72a3bc7e82fce68314a3a866031b7d8182e3c8a"
					},
					{
						"key": "sec-ch-ua",
						"value": "\".Not/A)Brand\";v=\"99\", \"Google Chrome\";v=\"103\", \"Chromium\";v=\"103\""
					},
					{
						"key": "sec-ch-ua-mobile",
						"value": "?0"
					},
					{
						"key": "sec-ch-ua-platform",
						"value": "\"Linux\""
					}
				],
				"url": {
					"raw": "https://svctest1.groceryoutlet.com/api/orderguide/getpreorderpoolitems?sowLogID=1021021",
					"protocol": "https",
					"host": [
						"svctest1",
						"groceryoutlet",
						"com"
					],
					"path": [
						"api",
						"orderguide",
						"getpreorderpoolitems"
					],
					"query": [
						{
							"key": "sowLogID",
							"value": "1021021"
						}
					]
				}
			},
			"response": []
		},
		{
			"name": "TC02_Validate the API response for input parameter",
			"request": {
				"method": "GET",
				"header": [
					{
						"key": "Accept",
						"value": "application/json, text/plain, */*"
					},
					{
						"key": "Accept-Language",
						"value": "en-GB,en-US;q=0.9,en;q=0.8"
					},
					{
						"key": "Cache-Control",
						"value": "no-cache, no-store, must-revalidate"
					},
					{
						"key": "Connection",
						"value": "keep-alive"
					},
					{
						"key": "Cookie",
						"value": "_ga=GA1.2.1629569301.1665497888; _fbp=fb.1.1665497888654.1290370928; __qca=P0-83208946-1665497888970"
					},
					{
						"key": "Expires",
						"value": "0"
					},
					{
						"key": "Origin",
						"value": "https://test1.groceryoutlet.com"
					},
					{
						"key": "Pragma",
						"value": "no-cache"
					},
					{
						"key": "Referer",
						"value": "https://test1.groceryoutlet.com/"
					},
					{
						"key": "Sec-Fetch-Dest",
						"value": "empty"
					},
					{
						"key": "Sec-Fetch-Mode",
						"value": "cors"
					},
					{
						"key": "Sec-Fetch-Site",
						"value": "same-site"
					},
					{
						"key": "User-Agent",
						"value": "Mozilla/5.0 (X11; Linux x86_64) AppleWebKit/537.36 (KHTML, like Gecko) Chrome/103.0.0.0 Safari/537.36"
					},
					{
						"key": "X-XSRF-Token",
						"value": "L3BitUIApWiGXGVW7QtlP7smL5XIoMbQ3PTCyw1SBX8WlJJMBPCtfz3OfaTHEYCywv-5-vvubWKvdR05FhhncjsNdrA1:p4N8w8Pkrw14fMEolytxt-Tj1A6UayE_nN_r4LDwQvTMmKX2QGqxmX0O35whiw9QCz4GqJ-6cwyqTIjLEvBbhOgjj44Y2N7xwZps610ba86va3ev5SYaAjLzrcKDWXWICil-jA2"
					},
					{
						"key": "api-token",
						"value": "Ac72a3bc7e82fce68314a3a866031b7d8182e3c8a"
					},
					{
						"key": "sec-ch-ua",
						"value": "\".Not/A)Brand\";v=\"99\", \"Google Chrome\";v=\"103\", \"Chromium\";v=\"103\""
					},
					{
						"key": "sec-ch-ua-mobile",
						"value": "?0"
					},
					{
						"key": "sec-ch-ua-platform",
						"value": "\"Linux\""
					}
				],
				"url": {
					"raw": "https://svctest1.groceryoutlet.com/api/orderguide/getpreorderpoolitems?sowLogID=1021021",
					"protocol": "https",
					"host": [
						"svctest1",
						"groceryoutlet",
						"com"
					],
					"path": [
						"api",
						"orderguide",
						"getpreorderpoolitems"
					],
					"query": [
						{
							"key": "sowLogID",
							"value": "1021021"
						}
					]
				}
			},
			"response": []
		},
		{
			"name": "TC03_Validate the API using POST method instead of GET",
			"request": {
				"method": "GET",
				"header": [
					{
						"key": "Accept",
						"value": "application/json, text/plain, */*"
					},
					{
						"key": "Accept-Language",
						"value": "en-GB,en-US;q=0.9,en;q=0.8"
					},
					{
						"key": "Cache-Control",
						"value": "no-cache, no-store, must-revalidate"
					},
					{
						"key": "Connection",
						"value": "keep-alive"
					},
					{
						"key": "Cookie",
						"value": "_ga=GA1.2.1629569301.1665497888; _fbp=fb.1.1665497888654.1290370928; __qca=P0-83208946-1665497888970"
					},
					{
						"key": "Expires",
						"value": "0"
					},
					{
						"key": "Origin",
						"value": "https://test1.groceryoutlet.com"
					},
					{
						"key": "Pragma",
						"value": "no-cache"
					},
					{
						"key": "Referer",
						"value": "https://test1.groceryoutlet.com/"
					},
					{
						"key": "Sec-Fetch-Dest",
						"value": "empty"
					},
					{
						"key": "Sec-Fetch-Mode",
						"value": "cors"
					},
					{
						"key": "Sec-Fetch-Site",
						"value": "same-site"
					},
					{
						"key": "User-Agent",
						"value": "Mozilla/5.0 (X11; Linux x86_64) AppleWebKit/537.36 (KHTML, like Gecko) Chrome/103.0.0.0 Safari/537.36"
					},
					{
						"key": "X-XSRF-Token",
						"value": "L3BitUIApWiGXGVW7QtlP7smL5XIoMbQ3PTCyw1SBX8WlJJMBPCtfz3OfaTHEYCywv-5-vvubWKvdR05FhhncjsNdrA1:p4N8w8Pkrw14fMEolytxt-Tj1A6UayE_nN_r4LDwQvTMmKX2QGqxmX0O35whiw9QCz4GqJ-6cwyqTIjLEvBbhOgjj44Y2N7xwZps610ba86va3ev5SYaAjLzrcKDWXWICil-jA2"
					},
					{
						"key": "api-token",
						"value": "Ac72a3bc7e82fce68314a3a866031b7d8182e3c8a"
					},
					{
						"key": "sec-ch-ua",
						"value": "\".Not/A)Brand\";v=\"99\", \"Google Chrome\";v=\"103\", \"Chromium\";v=\"103\""
					},
					{
						"key": "sec-ch-ua-mobile",
						"value": "?0"
					},
					{
						"key": "sec-ch-ua-platform",
						"value": "\"Linux\""
					}
				],
				"url": {
					"raw": "https://svctest1.groceryoutlet.com/api/orderguide/getpreorderpoolitems?sowLogID=1021021",
					"protocol": "https",
					"host": [
						"svctest1",
						"groceryoutlet",
						"com"
					],
					"path": [
						"api",
						"orderguide",
						"getpreorderpoolitems"
					],
					"query": [
						{
							"key": "sowLogID",
							"value": "1021021"
						}
					]
				}
			},
			"response": []
		},
		{
			"name": "TC04_Validate Response for invalid URL",
			"request": {
				"method": "GET",
				"header": [
					{
						"key": "Accept",
						"value": "application/json, text/plain, */*"
					},
					{
						"key": "Accept-Language",
						"value": "en-GB,en-US;q=0.9,en;q=0.8"
					},
					{
						"key": "Cache-Control",
						"value": "no-cache, no-store, must-revalidate"
					},
					{
						"key": "Connection",
						"value": "keep-alive"
					},
					{
						"key": "Cookie",
						"value": "_ga=GA1.2.1629569301.1665497888; _fbp=fb.1.1665497888654.1290370928; __qca=P0-83208946-1665497888970"
					},
					{
						"key": "Expires",
						"value": "0"
					},
					{
						"key": "Origin",
						"value": "https://test1.groceryoutlet.com"
					},
					{
						"key": "Pragma",
						"value": "no-cache"
					},
					{
						"key": "Referer",
						"value": "https://test1.groceryoutlet.com/"
					},
					{
						"key": "Sec-Fetch-Dest",
						"value": "empty"
					},
					{
						"key": "Sec-Fetch-Mode",
						"value": "cors"
					},
					{
						"key": "Sec-Fetch-Site",
						"value": "same-site"
					},
					{
						"key": "User-Agent",
						"value": "Mozilla/5.0 (X11; Linux x86_64) AppleWebKit/537.36 (KHTML, like Gecko) Chrome/103.0.0.0 Safari/537.36"
					},
					{
						"key": "X-XSRF-Token",
						"value": "L3BitUIApWiGXGVW7QtlP7smL5XIoMbQ3PTCyw1SBX8WlJJMBPCtfz3OfaTHEYCywv-5-vvubWKvdR05FhhncjsNdrA1:p4N8w8Pkrw14fMEolytxt-Tj1A6UayE_nN_r4LDwQvTMmKX2QGqxmX0O35whiw9QCz4GqJ-6cwyqTIjLEvBbhOgjj44Y2N7xwZps610ba86va3ev5SYaAjLzrcKDWXWICil-jA2"
					},
					{
						"key": "api-token",
						"value": "Ac72a3bc7e82fce68314a3a866031b7d8182e3c8a"
					},
					{
						"key": "sec-ch-ua",
						"value": "\".Not/A)Brand\";v=\"99\", \"Google Chrome\";v=\"103\", \"Chromium\";v=\"103\""
					},
					{
						"key": "sec-ch-ua-mobile",
						"value": "?0"
					},
					{
						"key": "sec-ch-ua-platform",
						"value": "\"Linux\""
					}
				],
				"url": {
					"raw": "https://svctest1.groceryoutlet.com/api/orderguide/getpreorderpoolitems?sowLogID=1021021",
					"protocol": "https",
					"host": [
						"svctest1",
						"groceryoutlet",
						"com"
					],
					"path": [
						"api",
						"orderguide",
						"getpreorderpoolitems"
					],
					"query": [
						{
							"key": "sowLogID",
							"value": "1021021"
						}
					]
				}
			},
			"response": []
		},
		{
			"name": "TC06_Schema Validation for Input parameter \"sowLogID\"",
			"request": {
				"method": "GET",
				"header": [
					{
						"key": "Accept",
						"value": "application/json, text/plain, */*"
					},
					{
						"key": "Accept-Language",
						"value": "en-GB,en-US;q=0.9,en;q=0.8"
					},
					{
						"key": "Cache-Control",
						"value": "no-cache, no-store, must-revalidate"
					},
					{
						"key": "Connection",
						"value": "keep-alive"
					},
					{
						"key": "Cookie",
						"value": "_ga=GA1.2.1629569301.1665497888; _fbp=fb.1.1665497888654.1290370928; __qca=P0-83208946-1665497888970"
					},
					{
						"key": "Expires",
						"value": "0"
					},
					{
						"key": "Origin",
						"value": "https://test1.groceryoutlet.com"
					},
					{
						"key": "Pragma",
						"value": "no-cache"
					},
					{
						"key": "Referer",
						"value": "https://test1.groceryoutlet.com/"
					},
					{
						"key": "Sec-Fetch-Dest",
						"value": "empty"
					},
					{
						"key": "Sec-Fetch-Mode",
						"value": "cors"
					},
					{
						"key": "Sec-Fetch-Site",
						"value": "same-site"
					},
					{
						"key": "User-Agent",
						"value": "Mozilla/5.0 (X11; Linux x86_64) AppleWebKit/537.36 (KHTML, like Gecko) Chrome/103.0.0.0 Safari/537.36"
					},
					{
						"key": "X-XSRF-Token",
						"value": "L3BitUIApWiGXGVW7QtlP7smL5XIoMbQ3PTCyw1SBX8WlJJMBPCtfz3OfaTHEYCywv-5-vvubWKvdR05FhhncjsNdrA1:p4N8w8Pkrw14fMEolytxt-Tj1A6UayE_nN_r4LDwQvTMmKX2QGqxmX0O35whiw9QCz4GqJ-6cwyqTIjLEvBbhOgjj44Y2N7xwZps610ba86va3ev5SYaAjLzrcKDWXWICil-jA2"
					},
					{
						"key": "api-token",
						"value": "Ac72a3bc7e82fce68314a3a866031b7d8182e3c8a"
					},
					{
						"key": "sec-ch-ua",
						"value": "\".Not/A)Brand\";v=\"99\", \"Google Chrome\";v=\"103\", \"Chromium\";v=\"103\""
					},
					{
						"key": "sec-ch-ua-mobile",
						"value": "?0"
					},
					{
						"key": "sec-ch-ua-platform",
						"value": "\"Linux\""
					}
				],
				"url": {
					"raw": "https://svctest1.groceryoutlet.com/api/orderguide/getpreorderpoolitems?sowLogID=1021021",
					"protocol": "https",
					"host": [
						"svctest1",
						"groceryoutlet",
						"com"
					],
					"path": [
						"api",
						"orderguide",
						"getpreorderpoolitems"
					],
					"query": [
						{
							"key": "sowLogID",
							"value": "1021021"
						}
					]
				}
			},
			"response": []
		},
		{
			"name": "TC07_Check for Input parameter \"sowLogID\" as blank",
			"request": {
				"method": "GET",
				"header": [
					{
						"key": "Accept",
						"value": "application/json, text/plain, */*"
					},
					{
						"key": "Accept-Language",
						"value": "en-GB,en-US;q=0.9,en;q=0.8"
					},
					{
						"key": "Cache-Control",
						"value": "no-cache, no-store, must-revalidate"
					},
					{
						"key": "Connection",
						"value": "keep-alive"
					},
					{
						"key": "Cookie",
						"value": "_ga=GA1.2.1629569301.1665497888; _fbp=fb.1.1665497888654.1290370928; __qca=P0-83208946-1665497888970"
					},
					{
						"key": "Expires",
						"value": "0"
					},
					{
						"key": "Origin",
						"value": "https://test1.groceryoutlet.com"
					},
					{
						"key": "Pragma",
						"value": "no-cache"
					},
					{
						"key": "Referer",
						"value": "https://test1.groceryoutlet.com/"
					},
					{
						"key": "Sec-Fetch-Dest",
						"value": "empty"
					},
					{
						"key": "Sec-Fetch-Mode",
						"value": "cors"
					},
					{
						"key": "Sec-Fetch-Site",
						"value": "same-site"
					},
					{
						"key": "User-Agent",
						"value": "Mozilla/5.0 (X11; Linux x86_64) AppleWebKit/537.36 (KHTML, like Gecko) Chrome/103.0.0.0 Safari/537.36"
					},
					{
						"key": "X-XSRF-Token",
						"value": "L3BitUIApWiGXGVW7QtlP7smL5XIoMbQ3PTCyw1SBX8WlJJMBPCtfz3OfaTHEYCywv-5-vvubWKvdR05FhhncjsNdrA1:p4N8w8Pkrw14fMEolytxt-Tj1A6UayE_nN_r4LDwQvTMmKX2QGqxmX0O35whiw9QCz4GqJ-6cwyqTIjLEvBbhOgjj44Y2N7xwZps610ba86va3ev5SYaAjLzrcKDWXWICil-jA2"
					},
					{
						"key": "api-token",
						"value": "Ac72a3bc7e82fce68314a3a866031b7d8182e3c8a"
					},
					{
						"key": "sec-ch-ua",
						"value": "\".Not/A)Brand\";v=\"99\", \"Google Chrome\";v=\"103\", \"Chromium\";v=\"103\""
					},
					{
						"key": "sec-ch-ua-mobile",
						"value": "?0"
					},
					{
						"key": "sec-ch-ua-platform",
						"value": "\"Linux\""
					}
				],
				"url": {
					"raw": "https://svctest1.groceryoutlet.com/api/orderguide/getpreorderpoolitems?sowLogID=1021021",
					"protocol": "https",
					"host": [
						"svctest1",
						"groceryoutlet",
						"com"
					],
					"path": [
						"api",
						"orderguide",
						"getpreorderpoolitems"
					],
					"query": [
						{
							"key": "sowLogID",
							"value": "1021021"
						}
					]
				}
			},
			"response": []
		}
	]
}